setup.cfg
setup.py
src/echoip/__init__.py
src/echoip/providers.py
src/echoip/sources.py
src/pyechoip.egg-info/PKG-INFO
src/pyechoip.egg-info/SOURCES.txt
src/pyechoip.egg-info/dependency_links.txt
src/pyechoip.egg-info/requires.txt
src/pyechoip.egg-info/top_level.txt
test/test_IPProvider.py
test/test_JSONIPSource.py
test/test_multisourceIPProvider.py
test/test_simpleIPSource.py
test/test_sourceFactory.py