Metadata-Version: 1.0
Name: pyechoip
Version: 1.2
Summary: A generic library for getting your externally visible IP address in python.
Home-page: https://github.com/eflee/pyechoip
Author: Eli Flesher
Author-email: eli@eflee.us
License: Apache
Keywords: ip network
Platform: UNKNOWN
